WgLestaAPI/__init__.py
WgLestaAPI/Application.py
WgLestaAPI/Constants.py
WgLestaAPI/Exceptions.py
WgLestaAPI/Utils.py
wglestaapi-1.1.0.dist-info/LICENSE
wglestaapi-1.1.0.dist-info/METADATA
wglestaapi-1.1.0.dist-info/WHEEL
wglestaapi-1.1.0.dist-info/RECORD
