Metadata-Version: 2.1
Name: WgLestaAPI
Version: 1.1.0
Summary: Unofficial Python library that implements the Wargaming.net API and Lesta Games API functionality
Home-page: https://github.com/tankalxat34/WgLestaAPI
License: MIT
Author: Alexander Podstrechnyy
Author-email: tankalxat34@gmail.com
Requires-Python: >=3.6,<4.0
Classifier: License :: OSI Approved :: MIT License
Classifier: Programming Language :: Python :: 3
Classifier: Programming Language :: Python :: 3.6
Classifier: Programming Language :: Python :: 3.7
Classifier: Programming Language :: Python :: 3.8
Classifier: Programming Language :: Python :: 3.9
Classifier: Programming Language :: Python :: 3.10
Classifier: Programming Language :: Python :: 3.11
Classifier: Programming Language :: Python :: 3.12
Requires-Dist: aiohttp (>=3.9)
Requires-Dist: urllib3 (>=2.2)
Project-URL: Repository, https://github.com/tankalxat34/WgLestaAPI
Project-URL: homepage, https://github.com/tankalxat34/WgLestaAPI
